[
    {
      "name": "1337x",
      "public": true,
      "categories": [
        "All",
        "Movies",
        "TV",
        "Games",
        "Music",
        "Anime",
        "Applications",
        "Documentaries",
        "Xxx",
        "Other",
        "Top100"
      ]
    },
    {
      "name": "Eztv",
      "public": true,
      "categories": ["All"]
    },
    {
      "name": "IpTorrents",
      "public": false,
      "categories": ["All", "Movies", "TV", "Games", "Music"]
    },
    {
      "name": "KickassTorrents",
      "public": true,
      "categories": [
        "All",
        "Movies",
        "TV",
        "Music",
        "Games",
        "Books",
        "Applications",
        "Anime"
      ]
    },
    {
      "name": "Limetorrents",
      "public": true,
      "categories": ["All", "Movies", "TV", "Games", "Music", "Applications", "Anime"]
    },
    {
      "name": "Rarbg",
      "public": true,
      "categories": ["All", "Movies", "XXX", "Games", "TV", "Music", "Apps", "Books"]
    },
    {
      "name": "ThePirateBay",
      "public": true,
      "categories": [
        "All",
        "Audio",
        "Video",
        "Applications",
        "Games",
        "Porn",
        "Other",
        "Top100"
      ]
    },
    {
      "name": "Torrent9",
      "public": true,
      "categories": ["All", "Movies", "TV", "Music", "Apps", "Books", "Top100"]
    },
    {
      "name": "TorrentLeech",
      "public": false,
      "categories": [
        "All",
        "Movies",
        "TV",
        "Games",
        "Apps",
        "Education",
        "Animation",
        "Books",
        "Music",
        "Foreign"
      ]
    },
    {
      "name": "TorrentProject",
      "public": true,
      "categories": ["All"]
    },
    {
      "name": "Torrentz2",
      "public": true,
      "categories": ["All"]
    },
    {
      "name": "Yggtorrent",
      "public": false,
      "categories": [
        "All",
        "Videos",
        "Movies",
        "TV",
        "Emulation",
        "Games",
        "Applications",
        "Music",
        "Books",
        "GPS",
        "XXX"
      ]
    },
    {
      "name": "Yts",
      "public": true,
      "categories": ["All", "Movies"]
    }
  ]
  